cycore.cpython-37m-darwin.so
nes/__init__.py
nes/instructions.py
nes/meta.py
nes/peripherals.py
nes/rom.py
nes/tests.py
nes/utils.py
nes/cycore/__init__.py
nes/cycore/apu.cpython-37m-darwin.so
nes/cycore/bitwise.cpython-37m-darwin.so
nes/cycore/carts.cpython-37m-darwin.so
nes/cycore/memory.cpython-37m-darwin.so
nes/cycore/mos6502.cpython-37m-darwin.so
nes/cycore/ppu.cpython-37m-darwin.so
nes/cycore/system.cpython-37m-darwin.so
nes/pycore/__init__.py
nes/pycore/bitwise.py
nes/pycore/carts.py
nes/pycore/memory.py
nes/pycore/mos6502.py
nes/pycore/ppu.py
nes/pycore/system.py
tests/__init__.py
pyntendo-0.0.8.dist-info/LICENSE
pyntendo-0.0.8.dist-info/METADATA
pyntendo-0.0.8.dist-info/WHEEL
pyntendo-0.0.8.dist-info/top_level.txt
pyntendo-0.0.8.dist-info/RECORD
