Metadata-Version: 2.1
Name: pyntendo
Version: 0.0.8
Summary: A Nintendo Entertainment System (NES) emulator in Python and Cython
Home-page: https://github.com/jameskmurphy/nes
Author: James Murphy
Author-email: jkmurphy314@gmail.com
License: UNKNOWN
Platform: UNKNOWN
Classifier: Programming Language :: Python :: 3
Classifier: License :: OSI Approved :: MIT License
Classifier: Operating System :: OS Independent
Requires-Python: >=3.6
